silfont/__init__.py
silfont/comp.py
silfont/core.py
silfont/etutil.py
silfont/feax_ast.py
silfont/feax_lexer.py
silfont/feax_parser.py
silfont/ftml.py
silfont/ftml_builder.py
silfont/gfr.py
silfont/harfbuzz.py
silfont/ipython.py
silfont/ufo.py
silfont/util.py
silfont/data/required_chars.csv
silfont/data/required_chars.md
silfont/fbtests/__init__.py
silfont/fbtests/silnotcjk.py
silfont/fbtests/silttfchecks.py
silfont/fbtests/ttfchecks.py
silfont/scripts/__init__.py
silfont/scripts/psfaddanchors.py
silfont/scripts/psfbuildcomp.py
silfont/scripts/psfbuildcompgc.py
silfont/scripts/psfbuildfea.py
silfont/scripts/psfchangegdlnames.py
silfont/scripts/psfchangettfglyphnames.py
silfont/scripts/psfcheckbasicchars.py
silfont/scripts/psfcheckclassorders.py
silfont/scripts/psfcheckftml.py
silfont/scripts/psfcheckglyphinventory.py
silfont/scripts/psfcheckinterpolatable.py
silfont/scripts/psfcheckproject.py
silfont/scripts/psfcompdef2xml.py
silfont/scripts/psfcompressgr.py
silfont/scripts/psfcopyglyphs.py
silfont/scripts/psfcopymeta.py
silfont/scripts/psfcreateinstances.py
silfont/scripts/psfcsv2comp.py
silfont/scripts/psfdeflang.py
silfont/scripts/psfdeleteglyphs.py
silfont/scripts/psfdupglyphs.py
silfont/scripts/psfexportanchors.py
silfont/scripts/psfexportmarkcolors.py
silfont/scripts/psfexportpsnames.py
silfont/scripts/psfexportunicodes.py
silfont/scripts/psffixffglifs.py
silfont/scripts/psffixfontlab.py
silfont/scripts/psfftml2TThtml.py
silfont/scripts/psfftml2odt.py
silfont/scripts/psfgetglyphnames.py
silfont/scripts/psfglyphs2ufo.py
silfont/scripts/psfmakedeprecated.py
silfont/scripts/psfmakefea.py
silfont/scripts/psfmakescaledshifted.py
silfont/scripts/psfmakewoffmetadata.py
silfont/scripts/psfnormalize.py
silfont/scripts/psfpreflightversion.py
silfont/scripts/psfremovegliflibkeys.py
silfont/scripts/psfrenameglyphs.py
silfont/scripts/psfrunfbchecks.py
silfont/scripts/psfsetassocfeat.py
silfont/scripts/psfsetassocuids.py
silfont/scripts/psfsetdummydsig.py
silfont-1.8.0.dist-info/LICENSE
silfont-1.8.0.dist-info/METADATA
silfont-1.8.0.dist-info/WHEEL
silfont-1.8.0.dist-info/entry_points.txt
silfont-1.8.0.dist-info/top_level.txt
silfont-1.8.0.dist-info/RECORD
