Metadata-Version: 2.1
Name: silfont
Version: 1.8.0
Summary: A growing collection of font utilities in Python to help with font design and production. Developed and maintained by SIL International's WSTech team (formerly NRSI).
Author-email: SIL International <fonts@sil.org>
License: 
Project-URL: Home-Page, https://github.com/silnrsi/pysilfont
Classifier: Environment :: Console
Classifier: Programming Language :: Python :: 3.8
Classifier: Intended Audience :: Developers
Classifier: License :: OSI Approved :: MIT License
Classifier: Topic :: Text Processing :: Fonts
Requires-Python: >=3.8
License-File: LICENSE
Requires-Dist: MutatorMath
Requires-Dist: odfpy
Requires-Dist: defcon
Requires-Dist: fontMath
Requires-Dist: fontParts
Requires-Dist: fonttools
Requires-Dist: glyphsLib
Requires-Dist: ufo2ft
Requires-Dist: tabulate
Requires-Dist: lxml
Requires-Dist: lz4
